<item>
	
	<item>
		<title>[COLOR blue]V[/COLOR][COLOR yellow]i[/COLOR][COLOR blue]l[/COLOR][COLOR yellow]h[/COLOR][COLOR blue]a[/COLOR][COLOR yellow]o[/COLOR]   [B][COLOR yellow]Quim Roscas & Zeca Estacionancio 2003[/COLOR][/B]</title>
		<utube>rUMlwdiUcWA</utube>
		<thumbnail>https://i.imgur.com/L41Gm3D.png</thumbnail>
	</item>
	
	<item>
	    <title>[COLOR blue]V[/COLOR][COLOR yellow]i[/COLOR][COLOR blue]l[/COLOR][COLOR yellow]h[/COLOR][COLOR blue]a[/COLOR][COLOR yellow]o[/COLOR]   [B][COLOR yellow]Quim Roscas & Zeca Estacionancio festas do Castelo Vouzela 2019[/COLOR][/B]<title>[COLOR blue]V[/COLOR][COLOR yellow]i[/COLOR][COLOR blue]l[/COLOR][COLOR yellow]h[/COLOR][COLOR blue]a[/COLOR][COLOR yellow]o[/COLOR]   
		<utube>CTsmClN1vmQ</utube>
		<thumbnail>https://i.imgur.com/L41Gm3D.png</thumbnail>
	</item>
	
	<item>
	    <title>[COLOR blue]V[/COLOR][COLOR yellow]i[/COLOR][COLOR blue]l[/COLOR][COLOR yellow]h[/COLOR][COLOR blue]a[/COLOR][COLOR yellow]o[/COLOR]   [B][COLOR yellow]Festa Sra. Rosário Sta. Eufémia 18 Maio 2013 Guimarães[/COLOR][/B]<title>[COLOR blue]V[/COLOR][COLOR yellow]i[/COLOR][COLOR blue]l[/COLOR][COLOR yellow]h[/COLOR][COLOR blue]a[/COLOR][COLOR yellow]o[/COLOR]   
		<utube>iAWY_zfuY6U</utube>
		<thumbnail>https://i.imgur.com/L41Gm3D.png</thumbnail>
	</item>	

	<item>
	    <title>[COLOR blue]V[/COLOR][COLOR yellow]i[/COLOR][COLOR blue]l[/COLOR][COLOR yellow]h[/COLOR][COLOR blue]a[/COLOR][COLOR yellow]o[/COLOR]   [B][COLOR yellow]Quim Roscas & Zeca Estacionancio AO VIVO HD[/COLOR][/B]<title>[COLOR blue]V[/COLOR][COLOR yellow]i[/COLOR][COLOR blue]l[/COLOR][COLOR yellow]h[/COLOR][COLOR blue]a[/COLOR][COLOR yellow]o[/COLOR]   
		<utube>RCXxRZtunPs</utube>
		<thumbnail>https://i.imgur.com/L41Gm3D.png</thumbnail>
	</item>	
		